<?xml version="1.0"?>
<ElementData xmlns:xsi="http://www.w3.org/2001/XMLSchema-instance" xmlns:xsd="http://www.w3.org/2001/XMLSchema" xmlns="http://www.abb.com/800xA/Graphics">
  <FileVersion>1.0.0.3</FileVersion>
  <SystemVersion>6.0.0.103.271</SystemVersion>
  <ElementId>{7622fdb2-ff96-42b9-8949-4a636a3a9d25}:{9d361c36-63e7-4817-82e9-7964bf8ca9fc}</ElementId>
  <ElementName>PIDCtrl:fpe Ctrl Setup</ElementName>
  <ElementTypeId>{9b12a235-c19a-4ca3-a38f-eb1fdf913445}</ElementTypeId>
  <ElementTypeName>MAPL Faceplate Element PG2</ElementTypeName>
  <GraphicElement>
    <ObjectAware>true</ObjectAware>
    <UpdateInterval>0</UpdateInterval>
    <NumberOfViews>1</NumberOfViews>
    <BindMethod>0</BindMethod>
    <PresentationMode>3</PresentationMode>
    <AnimationRate>10</AnimationRate>
    <InhibitInput>LeftMouseClick</InhibitInput>
    <SubscriptionRate>1000</SubscriptionRate>
    <CustomViewSelection>-1</CustomViewSelection>
    <InputProperties />
    <ElementHostedInputItems />
    <UserEnumerations />
    <ExpressionVariables />
    <Views>
      <Views>
        <HotSpot>
          <X>NaN</X>
          <Y>NaN</Y>
        </HotSpot>
        <BackColor>Transparent</BackColor>
        <DefaultSize>
          <Width>350</Width>
          <Height>300</Height>
        </DefaultSize>
        <GraphicItems>
          <GraphicItem>
            <Name>_BackgroundColor</Name>
            <TypeName />
            <ElementInstanceIndex>0</ElementInstanceIndex>
            <PropertyDescriptions>
              <PropertyDescription Name="Name" Value="&quot;_BackgroundColor&quot;" />
              <PropertyDescription Name="Transform" Value="Empty" />
              <PropertyDescription Name="Visible" Value="True" />
              <PropertyDescription Name="AnchorStyle" Value="All" />
              <PropertyDescription Name="XPos" Value="0." />
              <PropertyDescription Name="YPos" Value="0." />
              <PropertyDescription Name="Width" Value="350." />
              <PropertyDescription Name="Height" Value="300." />
              <PropertyDescription Name="Rotation" Value="0" />
              <PropertyDescription Name="ColorSchemeSelection" Value="0" />
              <PropertyDescription Name="ColorSelection" Value="7" />
            </PropertyDescriptions>
            <InputItems />
            <ObjectAware>false</ObjectAware>
          </GraphicItem>
          <GraphicItem>
            <Name>MAPL_ContentBox1</Name>
            <TypeName />
            <ElementInstanceIndex>0</ElementInstanceIndex>
            <PropertyDescriptions>
              <PropertyDescription Name="Name" Value="&quot;MAPL_ContentBox1&quot;" />
              <PropertyDescription Name="Transform" Value="Empty" />
              <PropertyDescription Name="Visible" Value="True" />
              <PropertyDescription Name="AnchorStyle" Value="TopLeftRight" />
              <PropertyDescription Name="XPos" Value="5." />
              <PropertyDescription Name="YPos" Value="5." />
              <PropertyDescription Name="Width" Value="340." />
              <PropertyDescription Name="Height" Value="135." />
              <PropertyDescription Name="Rotation" Value="0" />
              <PropertyDescription Name="AlarmConditionState" Value="0" />
              <PropertyDescription Name="AlarmPriorityLevel" Value="0" />
              <PropertyDescription Name="AlarmsInhibited" Value="False" />
              <PropertyDescription Name="ColorSchemeSelection" Value="0" />
              <PropertyDescription Name="Description1Font" Value="$'ft::ABB Marine Customization:Arial_11pt_Regular'" />
              <PropertyDescription Name="Description1Text" Value="&quot;&quot;" />
              <PropertyDescription Name="Description1Visibility" Value="False" />
              <PropertyDescription Name="Description2Font" Value="$'ft::ABB Marine Customization:Arial_11pt_Regular'" />
              <PropertyDescription Name="Description2Text" Value="&quot;&quot;" />
              <PropertyDescription Name="Description2Visibility" Value="False" />
              <PropertyDescription Name="HeaderBlinking" Value="False" />
              <PropertyDescription Name="HeaderFont" Value="$'ft::ABB Marine Customization:Arial_16pt_Bold'" />
              <PropertyDescription Name="HeaderHighlight" Value="False" />
              <PropertyDescription Name="HeaderText" Value="&quot;&quot;" />
              <PropertyDescription Name="HeaderVisibility" Value="False" />
              <PropertyDescription Name="InhibitAlarmAccent" Value="True" />
              <PropertyDescription Name="InteractionVisibility" Value="False" />
              <PropertyDescription Name="ItemInactive" Value="False" />
              <PropertyDescription Name="ParentObjectName" Value="&quot;&quot;" />
              <PropertyDescription Name="StaticContent" Value="False" />
              <PropertyDescription Name="UnitFont" Value="$'ft::ABB Marine Customization:Arial_16pt_Regular'" />
              <PropertyDescription Name="UnitText" Value="&quot;&quot;" />
              <PropertyDescription Name="UnitVisibility" Value="False" />
              <PropertyDescription Name="ValueFont" Value="$'ft::ABB Marine Customization:Arial_24pt_Bold'" />
              <PropertyDescription Name="ValueText" Value="&quot;&quot;" />
              <PropertyDescription Name="ValueVisibility" Value="False" />
            </PropertyDescriptions>
            <InputItems />
            <ObjectAware>false</ObjectAware>
          </GraphicItem>
          <GraphicItem>
            <Name>Deviation_Static</Name>
            <TypeName />
            <ElementInstanceIndex>0</ElementInstanceIndex>
            <PropertyDescriptions>
              <PropertyDescription Name="Name" Value="&quot;Deviation_Static&quot;" />
              <PropertyDescription Name="Transform" Value="Empty" />
              <PropertyDescription Name="Visible" Value="True" />
              <PropertyDescription Name="AnchorStyle" Value="Custom" />
              <PropertyDescription Name="XPos" Value="15." />
              <PropertyDescription Name="YPos" Value="45." />
              <PropertyDescription Name="Width" Value="170." />
              <PropertyDescription Name="Height" Value="25." />
              <PropertyDescription Name="Rotation" Value="0" />
              <PropertyDescription Name="ColorSchemeSelection" Value="0" />
              <PropertyDescription Name="EnableClip" Value="False" />
              <PropertyDescription Name="HorizonalAlign" Value="Near" />
              <PropertyDescription Name="InputText" Value="$'nt::PIDCtrl_NLS:NLSID_ProcessLib_PIDCtrl_Deviation'" />
              <PropertyDescription Name="TextColor" Value="11" />
              <PropertyDescription Name="TextEnhancement" Value="0" />
              <PropertyDescription Name="TextFont" Value="$'ft::ABB Marine Customization:Arial_11pt_Regular'" />
              <PropertyDescription Name="TextTransparency" Value="0" />
              <PropertyDescription Name="VerticalAlign" Value="Middle" />
              <PropertyDescription Name="WrapText" Value="False" />
            </PropertyDescriptions>
            <InputItems />
            <ObjectAware>false</ObjectAware>
          </GraphicItem>
          <GraphicItem>
            <Name>Deviation Alarm Delay Static</Name>
            <TypeName />
            <ElementInstanceIndex>0</ElementInstanceIndex>
            <PropertyDescriptions>
              <PropertyDescription Name="Name" Value="&quot;Deviation Alarm Delay Static&quot;" />
              <PropertyDescription Name="Transform" Value="Empty" />
              <PropertyDescription Name="Visible" Value="True" />
              <PropertyDescription Name="AnchorStyle" Value="Custom" />
              <PropertyDescription Name="XPos" Value="15." />
              <PropertyDescription Name="YPos" Value="75." />
              <PropertyDescription Name="Width" Value="170." />
              <PropertyDescription Name="Height" Value="25." />
              <PropertyDescription Name="Rotation" Value="0" />
              <PropertyDescription Name="ColorSchemeSelection" Value="0" />
              <PropertyDescription Name="EnableClip" Value="False" />
              <PropertyDescription Name="HorizonalAlign" Value="Near" />
              <PropertyDescription Name="InputText" Value="$'nt::PIDCtrl_NLS:NLSID_ProcessLib_PIDCtrl_DeviationAlarmDelay'" />
              <PropertyDescription Name="TextColor" Value="11" />
              <PropertyDescription Name="TextEnhancement" Value="0" />
              <PropertyDescription Name="TextFont" Value="$'ft::ABB Marine Customization:Arial_11pt_Regular'" />
              <PropertyDescription Name="TextTransparency" Value="0" />
              <PropertyDescription Name="VerticalAlign" Value="Middle" />
              <PropertyDescription Name="WrapText" Value="False" />
            </PropertyDescriptions>
            <InputItems />
            <ObjectAware>false</ObjectAware>
          </GraphicItem>
          <GraphicItem>
            <Name>Setpoint Deadband Static</Name>
            <TypeName />
            <ElementInstanceIndex>0</ElementInstanceIndex>
            <PropertyDescriptions>
              <PropertyDescription Name="Name" Value="&quot;Setpoint Deadband Static&quot;" />
              <PropertyDescription Name="Transform" Value="Empty" />
              <PropertyDescription Name="Visible" Value="True" />
              <PropertyDescription Name="AnchorStyle" Value="Custom" />
              <PropertyDescription Name="XPos" Value="15." />
              <PropertyDescription Name="YPos" Value="15." />
              <PropertyDescription Name="Width" Value="170." />
              <PropertyDescription Name="Height" Value="25." />
              <PropertyDescription Name="Rotation" Value="0" />
              <PropertyDescription Name="ColorSchemeSelection" Value="0" />
              <PropertyDescription Name="EnableClip" Value="False" />
              <PropertyDescription Name="HorizonalAlign" Value="Near" />
              <PropertyDescription Name="InputText" Value="$'nt::PIDCtrl_NLS:NLSID_ProcessLib_PIDCtrl_SetpointDeadband'" />
              <PropertyDescription Name="TextColor" Value="11" />
              <PropertyDescription Name="TextEnhancement" Value="0" />
              <PropertyDescription Name="TextFont" Value="$'ft::ABB Marine Customization:Arial_11pt_Regular'" />
              <PropertyDescription Name="TextTransparency" Value="0" />
              <PropertyDescription Name="VerticalAlign" Value="Middle" />
              <PropertyDescription Name="WrapText" Value="False" />
            </PropertyDescriptions>
            <InputItems />
            <ObjectAware>false</ObjectAware>
          </GraphicItem>
          <GraphicItem>
            <Name>Deviation Input Field</Name>
            <TypeName>Interactive:Input Field</TypeName>
            <ElementInstanceIndex>0</ElementInstanceIndex>
            <PropertyDescriptions>
              <PropertyDescription Name="Name" Value="&quot;Deviation Input Field&quot;" />
              <PropertyDescription Name="Transform" Value="Empty" />
              <PropertyDescription Name="Visible" Value="True" />
              <PropertyDescription Name="AnchorStyle" Value="Custom" />
              <PropertyDescription Name="XPos" Value="175." />
              <PropertyDescription Name="YPos" Value="45." />
              <PropertyDescription Name="Width" Value="105." />
              <PropertyDescription Name="Height" Value="25." />
              <PropertyDescription Name="Rotation" Value="0" />
              <PropertyDescription Name="AlarmConditionState" Value="0" />
              <PropertyDescription Name="AlarmPriorityLevel" Value="0" />
              <PropertyDescription Name="AlarmsInhibited" Value="False" />
              <PropertyDescription Name="ColorSchemeSelection" Value="0" />
              <PropertyDescription Name="Culture" Value="&quot;&quot;" />
              <PropertyDescription Name="DataQuality" Value="$'pr::PIDCtrl:Control Module:FPIntPar.FP_DevDB'#DataQuality" />
              <PropertyDescription Name="DataType" Value="Real" />
              <PropertyDescription Name="DateTimeFormatString" Value="&quot;&quot;" />
              <PropertyDescription Name="EnableSetpointApply" Value="$'pr::PIDCtrl:Control Module:FPIntPar.FP_DevDB'#IsWritable" />
              <PropertyDescription Name="EntryWindowOnTop" Value="False" />
              <PropertyDescription Name="HorizontalAlign" Value="Far" />
              <PropertyDescription Name="InhibitAlarmAccent" Value="False" />
              <PropertyDescription Name="InputWidth" Value="52." />
              <PropertyDescription Name="ItemInactive" Value="False" />
              <PropertyDescription Name="Maximum" Value="Empty" />
              <PropertyDescription Name="MaxNoOfChars" Value="0" />
              <PropertyDescription Name="Minimum" Value="Empty" />
              <PropertyDescription Name="NumberOfDecimals" Value="$'pr::PIDCtrl:Control Module:PV.Parameters.Fraction'" />
              <PropertyDescription Name="OverrideValue" Value="&quot;&quot;" />
              <PropertyDescription Name="PropertyReference" Value="$'pr::PIDCtrl:Control Module:FPIntPar.FP_DevDB'" />
              <PropertyDescription Name="StepSize" Value="1." />
              <PropertyDescription Name="TargetArrayIndices" Value="{-1}" />
              <PropertyDescription Name="TextColorValue" Value="1" />
              <PropertyDescription Name="TextFontUnit" Value="$'ft::ABB Marine Customization:Arial_11pt_Regular'" />
              <PropertyDescription Name="TextFontValue" Value="$'ft::ABB Marine Customization:Arial_11pt_Bold'" />
              <PropertyDescription Name="Tooltip" Value="$'nt::PIDCtrl_NLS:NLSID_ProcessLib_PIDCtrl_Tooltip_SetDeviation'" />
              <PropertyDescription Name="Unit" Value="&quot;&quot;" />
              <PropertyDescription Name="UnitPosition" Value="Right" />
              <PropertyDescription Name="UnitVisible" Value="False" />
              <PropertyDescription Name="ValueForced" Value="False" />
              <PropertyDescription Name="VerticalAlign" Value="Middle" />
              <PropertyDescription Name="WrapText" Value="False" />
            </PropertyDescriptions>
            <InputItems />
            <ObjectAware>false</ObjectAware>
          </GraphicItem>
          <GraphicItem>
            <Name>RadioButton Alarm Enable</Name>
            <TypeName />
            <ElementInstanceIndex>0</ElementInstanceIndex>
            <PropertyDescriptions>
              <PropertyDescription Name="Name" Value="&quot;RadioButton Alarm Enable&quot;" />
              <PropertyDescription Name="Transform" Value="Empty" />
              <PropertyDescription Name="Visible" Value="True" />
              <PropertyDescription Name="AnchorStyle" Value="Custom" />
              <PropertyDescription Name="XPos" Value="15." />
              <PropertyDescription Name="YPos" Value="105." />
              <PropertyDescription Name="Width" Value="220." />
              <PropertyDescription Name="Height" Value="25." />
              <PropertyDescription Name="Rotation" Value="0" />
              <PropertyDescription Name="AlarmConditionState" Value="0" />
              <PropertyDescription Name="AlarmPriorityLevel" Value="0" />
              <PropertyDescription Name="AlarmsInhibited" Value="False" />
              <PropertyDescription Name="ButtonActive" Value="True" />
              <PropertyDescription Name="Checked" Value="$'pr::PIDCtrl:Control Module:FPIntPar.FP_DevALEn'" />
              <PropertyDescription Name="ColorSchemeSelection" Value="0" />
              <PropertyDescription Name="DataQuality" Value="$'pr::PIDCtrl:Control Module:FPIntPar.FP_DevALEn'#DataQuality" />
              <PropertyDescription Name="EnableApplyCancelSessionFunctionality" Value="False" />
              <PropertyDescription Name="EnableInteraction" Value="$'pr::PIDCtrl:Control Module:FPIntPar.FP_DevALEn'#IsWritable" />
              <PropertyDescription Name="EnableTwoStepCommands" Value="False" />
              <PropertyDescription Name="GroupIndex" Value="-1" />
              <PropertyDescription Name="HorizontalAlignment" Value="Near" />
              <PropertyDescription Name="OptionText" Value="$'nt::PIDCtrl_NLS:NLSID_ProcessLib_PIDCtrl_DeviationAlarmEnable'" />
              <PropertyDescription Name="Target" Value="$'pr::PIDCtrl:Control Module:FPIntPar.FP_DevALEn'" />
              <PropertyDescription Name="TextFont" Value="$'ft::ABB Marine Customization:Arial_11pt_Bold'" />
              <PropertyDescription Name="Tooltip" Value="$'nt::PIDCtrl_NLS:NLSID_ProcessLib_PIDCtrl_Tooltip_SetEnableDeviationAlarm'" />
              <PropertyDescription Name="Value" Value="if $'pr::PIDCtrl:Control Module:FPIntPar.FP_DevALEn' then Variant(False) else Variant(True)" />
            </PropertyDescriptions>
            <InputItems />
            <ObjectAware>false</ObjectAware>
          </GraphicItem>
          <GraphicItem>
            <Name>Alarm Delay Input Field</Name>
            <TypeName>Interactive:Input Field</TypeName>
            <ElementInstanceIndex>0</ElementInstanceIndex>
            <PropertyDescriptions>
              <PropertyDescription Name="Name" Value="&quot;Alarm Delay Input Field&quot;" />
              <PropertyDescription Name="Transform" Value="Empty" />
              <PropertyDescription Name="Visible" Value="True" />
              <PropertyDescription Name="AnchorStyle" Value="Custom" />
              <PropertyDescription Name="XPos" Value="175." />
              <PropertyDescription Name="YPos" Value="75." />
              <PropertyDescription Name="Width" Value="105." />
              <PropertyDescription Name="Height" Value="25." />
              <PropertyDescription Name="Rotation" Value="0" />
              <PropertyDescription Name="AlarmConditionState" Value="0" />
              <PropertyDescription Name="AlarmPriorityLevel" Value="0" />
              <PropertyDescription Name="AlarmsInhibited" Value="False" />
              <PropertyDescription Name="ColorSchemeSelection" Value="0" />
              <PropertyDescription Name="Culture" Value="&quot;&quot;" />
              <PropertyDescription Name="DataQuality" Value="$'pr::PIDCtrl:Control Module:FPIntPar.FP_DevDlay'#DataQuality" />
              <PropertyDescription Name="DataType" Value="Time" />
              <PropertyDescription Name="DateTimeFormatString" Value="&quot;&quot;" />
              <PropertyDescription Name="EnableSetpointApply" Value="$'pr::PIDCtrl:Control Module:FPIntPar.FP_DevDlay'#IsWritable" />
              <PropertyDescription Name="EntryWindowOnTop" Value="False" />
              <PropertyDescription Name="HorizontalAlign" Value="Far" />
              <PropertyDescription Name="InhibitAlarmAccent" Value="False" />
              <PropertyDescription Name="InputWidth" Value="52." />
              <PropertyDescription Name="ItemInactive" Value="False" />
              <PropertyDescription Name="Maximum" Value="Empty" />
              <PropertyDescription Name="MaxNoOfChars" Value="0" />
              <PropertyDescription Name="Minimum" Value="Empty" />
              <PropertyDescription Name="NumberOfDecimals" Value="0" />
              <PropertyDescription Name="OverrideValue" Value="&quot;&quot;" />
              <PropertyDescription Name="PropertyReference" Value="$'pr::PIDCtrl:Control Module:FPIntPar.FP_DevDlay'" />
              <PropertyDescription Name="StepSize" Value="1." />
              <PropertyDescription Name="TargetArrayIndices" Value="{-1}" />
              <PropertyDescription Name="TextColorValue" Value="1" />
              <PropertyDescription Name="TextFontUnit" Value="$'ft::ABB Marine Customization:Arial_11pt_Regular'" />
              <PropertyDescription Name="TextFontValue" Value="$'ft::ABB Marine Customization:Arial_11pt_Bold'" />
              <PropertyDescription Name="Tooltip" Value="$'nt::PIDCtrl_NLS:NLSID_ProcessLib_PIDCtrl_Tooltip_SetDeviationAlarmDelay'" />
              <PropertyDescription Name="Unit" Value="&quot;&quot;" />
              <PropertyDescription Name="UnitPosition" Value="Right" />
              <PropertyDescription Name="UnitVisible" Value="False" />
              <PropertyDescription Name="ValueForced" Value="False" />
              <PropertyDescription Name="VerticalAlign" Value="Middle" />
              <PropertyDescription Name="WrapText" Value="False" />
            </PropertyDescriptions>
            <InputItems />
            <ObjectAware>false</ObjectAware>
          </GraphicItem>
          <GraphicItem>
            <Name>Setpoint Deadband Input field</Name>
            <TypeName>Interactive:Input Field</TypeName>
            <ElementInstanceIndex>0</ElementInstanceIndex>
            <PropertyDescriptions>
              <PropertyDescription Name="Name" Value="&quot;Setpoint Deadband Input field&quot;" />
              <PropertyDescription Name="Transform" Value="Empty" />
              <PropertyDescription Name="Visible" Value="True" />
              <PropertyDescription Name="AnchorStyle" Value="Custom" />
              <PropertyDescription Name="XPos" Value="175." />
              <PropertyDescription Name="YPos" Value="15." />
              <PropertyDescription Name="Width" Value="105." />
              <PropertyDescription Name="Height" Value="25." />
              <PropertyDescription Name="Rotation" Value="0" />
              <PropertyDescription Name="AlarmConditionState" Value="0" />
              <PropertyDescription Name="AlarmPriorityLevel" Value="0" />
              <PropertyDescription Name="AlarmsInhibited" Value="False" />
              <PropertyDescription Name="ColorSchemeSelection" Value="0" />
              <PropertyDescription Name="Culture" Value="&quot;&quot;" />
              <PropertyDescription Name="DataQuality" Value="$'pr::PIDCtrl:Control Module:FPIntPar.FP_DB'#DataQuality" />
              <PropertyDescription Name="DataType" Value="Real" />
              <PropertyDescription Name="DateTimeFormatString" Value="&quot;&quot;" />
              <PropertyDescription Name="EnableSetpointApply" Value="$'pr::PIDCtrl:Control Module:FPIntPar.FP_DB'#IsWritable" />
              <PropertyDescription Name="EntryWindowOnTop" Value="False" />
              <PropertyDescription Name="HorizontalAlign" Value="Far" />
              <PropertyDescription Name="InhibitAlarmAccent" Value="False" />
              <PropertyDescription Name="InputWidth" Value="52." />
              <PropertyDescription Name="ItemInactive" Value="False" />
              <PropertyDescription Name="Maximum" Value="Empty" />
              <PropertyDescription Name="MaxNoOfChars" Value="0" />
              <PropertyDescription Name="Minimum" Value="Empty" />
              <PropertyDescription Name="NumberOfDecimals" Value="$'pr::PIDCtrl:Control Module:PV.Parameters.Fraction'" />
              <PropertyDescription Name="OverrideValue" Value="&quot;&quot;" />
              <PropertyDescription Name="PropertyReference" Value="$'pr::PIDCtrl:Control Module:FPIntPar.FP_DB'" />
              <PropertyDescription Name="StepSize" Value="1." />
              <PropertyDescription Name="TargetArrayIndices" Value="{-1}" />
              <PropertyDescription Name="TextColorValue" Value="1" />
              <PropertyDescription Name="TextFontUnit" Value="$'ft::ABB Marine Customization:Arial_11pt_Regular'" />
              <PropertyDescription Name="TextFontValue" Value="$'ft::ABB Marine Customization:Arial_11pt_Bold'" />
              <PropertyDescription Name="Tooltip" Value="$'nt::PIDCtrl_NLS:NLSID_ProcessLib_PIDCtrl_Tooltip_SetSPDeadband'" />
              <PropertyDescription Name="Unit" Value="&quot;&quot;" />
              <PropertyDescription Name="UnitPosition" Value="Right" />
              <PropertyDescription Name="UnitVisible" Value="False" />
              <PropertyDescription Name="ValueForced" Value="False" />
              <PropertyDescription Name="VerticalAlign" Value="Middle" />
              <PropertyDescription Name="WrapText" Value="False" />
            </PropertyDescriptions>
            <InputItems />
            <ObjectAware>false</ObjectAware>
          </GraphicItem>
          <GraphicItem>
            <Name>MAPL_ContentBox2</Name>
            <TypeName />
            <ElementInstanceIndex>0</ElementInstanceIndex>
            <PropertyDescriptions>
              <PropertyDescription Name="Name" Value="&quot;MAPL_ContentBox2&quot;" />
              <PropertyDescription Name="Transform" Value="Empty" />
              <PropertyDescription Name="Visible" Value="$'pr::PIDCtrl:Control Module:FPIntPar.FP_Sim'#IsWritable" />
              <PropertyDescription Name="AnchorStyle" Value="TopLeftRight" />
              <PropertyDescription Name="XPos" Value="5." />
              <PropertyDescription Name="YPos" Value="145." />
              <PropertyDescription Name="Width" Value="340." />
              <PropertyDescription Name="Height" Value="45." />
              <PropertyDescription Name="Rotation" Value="0" />
              <PropertyDescription Name="AlarmConditionState" Value="0" />
              <PropertyDescription Name="AlarmPriorityLevel" Value="0" />
              <PropertyDescription Name="AlarmsInhibited" Value="False" />
              <PropertyDescription Name="ColorSchemeSelection" Value="0" />
              <PropertyDescription Name="Description1Font" Value="$'ft::ABB Marine Customization:Arial_11pt_Regular'" />
              <PropertyDescription Name="Description1Text" Value="&quot;&quot;" />
              <PropertyDescription Name="Description1Visibility" Value="False" />
              <PropertyDescription Name="Description2Font" Value="$'ft::ABB Marine Customization:Arial_11pt_Regular'" />
              <PropertyDescription Name="Description2Text" Value="&quot;&quot;" />
              <PropertyDescription Name="Description2Visibility" Value="False" />
              <PropertyDescription Name="HeaderBlinking" Value="False" />
              <PropertyDescription Name="HeaderFont" Value="$'ft::ABB Marine Customization:Arial_11pt_Bold'" />
              <PropertyDescription Name="HeaderHighlight" Value="False" />
              <PropertyDescription Name="HeaderText" Value="&quot;&quot;" />
              <PropertyDescription Name="HeaderVisibility" Value="True" />
              <PropertyDescription Name="InhibitAlarmAccent" Value="True" />
              <PropertyDescription Name="InteractionVisibility" Value="False" />
              <PropertyDescription Name="ItemInactive" Value="False" />
              <PropertyDescription Name="ParentObjectName" Value="&quot;xyz#123&quot;" />
              <PropertyDescription Name="StaticContent" Value="False" />
              <PropertyDescription Name="UnitFont" Value="$'ft::ABB Marine Customization:Arial_16pt_Regular'" />
              <PropertyDescription Name="UnitText" Value="&quot;&quot;" />
              <PropertyDescription Name="UnitVisibility" Value="False" />
              <PropertyDescription Name="ValueFont" Value="$'ft::ABB Marine Customization:Arial_24pt_Bold'" />
              <PropertyDescription Name="ValueText" Value="&quot;&quot;" />
              <PropertyDescription Name="ValueVisibility" Value="False" />
            </PropertyDescriptions>
            <InputItems />
            <ObjectAware>false</ObjectAware>
          </GraphicItem>
          <GraphicItem>
            <Name>MAPL_RadioButton1</Name>
            <TypeName />
            <ElementInstanceIndex>0</ElementInstanceIndex>
            <PropertyDescriptions>
              <PropertyDescription Name="Name" Value="&quot;MAPL_RadioButton1&quot;" />
              <PropertyDescription Name="Transform" Value="Empty" />
              <PropertyDescription Name="Visible" Value="$'pr::PIDCtrl:Control Module:FPIntPar.FP_Sim'#IsWritable" />
              <PropertyDescription Name="AnchorStyle" Value="Custom" />
              <PropertyDescription Name="XPos" Value="15." />
              <PropertyDescription Name="YPos" Value="155." />
              <PropertyDescription Name="Width" Value="220." />
              <PropertyDescription Name="Height" Value="25." />
              <PropertyDescription Name="Rotation" Value="0" />
              <PropertyDescription Name="AlarmConditionState" Value="0" />
              <PropertyDescription Name="AlarmPriorityLevel" Value="0" />
              <PropertyDescription Name="AlarmsInhibited" Value="False" />
              <PropertyDescription Name="ButtonActive" Value="True" />
              <PropertyDescription Name="Checked" Value="$'pr::PIDCtrl:Control Module:FPIntPar.FP_Sim'" />
              <PropertyDescription Name="ColorSchemeSelection" Value="0" />
              <PropertyDescription Name="DataQuality" Value="$'pr::PIDCtrl:Control Module:FPIntPar.FP_Sim'#DataQuality" />
              <PropertyDescription Name="EnableApplyCancelSessionFunctionality" Value="False" />
              <PropertyDescription Name="EnableInteraction" Value="$'pr::PIDCtrl:Control Module:FPIntPar.FP_Sim'#IsWritable" />
              <PropertyDescription Name="EnableTwoStepCommands" Value="False" />
              <PropertyDescription Name="GroupIndex" Value="401" />
              <PropertyDescription Name="HorizontalAlignment" Value="Near" />
              <PropertyDescription Name="OptionText" Value="$'nt::PIDCtrl_NLS:NLSID_ProcessLib_PIDCtrl_Simulation'" />
              <PropertyDescription Name="Target" Value="$'pr::PIDCtrl:Control Module:FPIntPar.FP_Sim'" />
              <PropertyDescription Name="TextFont" Value="$'ft::ABB Marine Customization:Arial_11pt_Bold'" />
              <PropertyDescription Name="Tooltip" Value="&quot;&quot;" />
              <PropertyDescription Name="Value" Value="!$'pr::PIDCtrl:Control Module:FPIntPar.FP_Sim'" />
            </PropertyDescriptions>
            <InputItems />
            <ObjectAware>false</ObjectAware>
          </GraphicItem>
        </GraphicItems>
      </Views>
    </Views>
  </GraphicElement>
</ElementData>